CHANGES.txt
MANIFEST.in
README.rst
setup.py
isotoma/__init__.py
isotoma.recipe.pound.egg-info/PKG-INFO
isotoma.recipe.pound.egg-info/SOURCES.txt
isotoma.recipe.pound.egg-info/dependency_links.txt
isotoma.recipe.pound.egg-info/entry_points.txt
isotoma.recipe.pound.egg-info/namespace_packages.txt
isotoma.recipe.pound.egg-info/not-zip-safe
isotoma.recipe.pound.egg-info/requires.txt
isotoma.recipe.pound.egg-info/top_level.txt
isotoma/recipe/__init__.py
isotoma/recipe/pound/__init__.py
isotoma/recipe/pound/apache.conf
isotoma/recipe/pound/backend.py
isotoma/recipe/pound/cycle.py
isotoma/recipe/pound/cyclescript.py
isotoma/recipe/pound/emergency.py
isotoma/recipe/pound/pound.cfg
isotoma/recipe/pound/util.py