Metadata-Version: 1.0
Name: isotoma.recipe.pound
Version: 0.1.13
Summary: Buildout recipes to configure the pound load balancer
Home-page: http://pypi.python.org/pypi/isotoma.recipe.pound
Author: Doug Winter
Author-email: doug.winter@isotoma.com
License: Apache Software License
Keywords: proxy buildout pound
Platform: UNKNOWN
Classifier: Framework :: Buildout
Classifier: Intended Audience :: System Administrators
Classifier: Operating System :: POSIX
Classifier: License :: OSI Approved :: Apache Software License
